boozo/__init__.py
boozo/__main__.py
boozo/config/__init__.py
boozo/config/_log_.py
boozo/config/bootstrap.py
boozo/config/env.py
boozo/data/gitignore
boozo/utils/__init__.py
boozo/utils/cast.py
boozo/utils/color.py
boozo/utils/common.py
boozo/utils/fio.py
boozo/utils/recurse.py
boozo/utils/snek.py
boozo/utils/timestamp.py
boozo/utils/typeformats.py
pyboozo-1.0.8.data/data/gitignore
pyboozo-1.0.8.dist-info/LICENSE
pyboozo-1.0.8.dist-info/METADATA
pyboozo-1.0.8.dist-info/WHEEL
pyboozo-1.0.8.dist-info/entry_points.txt
pyboozo-1.0.8.dist-info/top_level.txt
pyboozo-1.0.8.dist-info/RECORD
