Metadata-Version: 2.1
Name: pyboozo
Version: 1.0.8
Summary: An opinionated software development environment setup and configuration generator.
Home-page: https://github.com/skillplot/pyboozo
Author: skillplot
Author-email: skillplot@gmail.com
License: UNKNOWN
Project-URL: Download, https://github.com/skillplot/pyboozo/archive/1.0.8.tar.gz
Keywords: software development,configuration generator,environment setup
Platform: UNKNOWN
Classifier: Development Status :: 5 - Production/Stable
Classifier: Intended Audience :: Developers
Classifier: Topic :: Software Development :: Build Tools
Classifier: License :: OSI Approved :: Apache Software License
Classifier: Operating System :: POSIX :: Linux
Classifier: Programming Language :: Python :: 3
Classifier: Programming Language :: Python :: 3.6
Classifier: Environment :: Console
Requires-Python: ~=3.6
Requires-Dist: easydict
Requires-Dist: PyYaml
Requires-Dist: arrow
Requires-Dist: click
